hallunox/__init__.py
hallunox/detector.py
hallunox/inference.py
hallunox/similarity_metrics.py
hallunox/training.py
hallunox/utils.py
hallunox-0.6.3.dist-info/licenses/LICENSE
hallunox-0.6.3.dist-info/METADATA
hallunox-0.6.3.dist-info/WHEEL
hallunox-0.6.3.dist-info/entry_points.txt
hallunox-0.6.3.dist-info/top_level.txt
hallunox-0.6.3.dist-info/RECORD
