Metadata-Version: 2.4
Name: hallunox
Version: 0.6.3
Summary: A confidence-aware routing system for LLM hallucination detection using multi-signal approach
Home-page: https://github.com/convai-innovations/hallunox
Author: Nandakishor M
Author-email: Nandakishor M <support@convaiinnovations.com>
Maintainer-email: "Convai Innovations Pvt. Ltd." <support@convaiinnovations.com>
License: AGPL-3.0
Project-URL: Homepage, https://convaiinnovations.com
Project-URL: Repository, https://github.com/convai-innovations/hallunox
Project-URL: Documentation, https://hallunox.readthedocs.io
Project-URL: Bug Reports, https://github.com/convai-innovations/hallunox/issues
Project-URL: Source Code, https://github.com/convai-innovations/hallunox
Keywords: hallucination-detection,llm,confidence-estimation,model-reliability,uncertainty-quantification,ai-safety
Classifier: Development Status :: 3 - Alpha
Classifier: Intended Audience :: Developers
Classifier: Intended Audience :: Science/Research
Classifier: License :: OSI Approved :: GNU Affero General Public License v3
Classifier: Operating System :: OS Independent
Classifier: Programming Language :: Python :: 3
Classifier: Programming Language :: Python :: 3.8
Classifier: Programming Language :: Python :: 3.9
Classifier: Programming Language :: Python :: 3.10
Classifier: Programming Language :: Python :: 3.11
Classifier: Topic :: Scientific/Engineering :: Artificial Intelligence
Classifier: Topic :: Software Development :: Libraries :: Python Modules
Requires-Python: >=3.8
License-File: LICENSE
Requires-Dist: torch>=1.13.0
Requires-Dist: transformers>=4.45.0
Requires-Dist: datasets>=2.0.0
Requires-Dist: FlagEmbedding>=1.2.0
Requires-Dist: scikit-learn>=1.0.0
Requires-Dist: numpy==1.26.4
Requires-Dist: tqdm>=4.64.0
Requires-Dist: pathlib
Requires-Dist: Pillow>=8.0.0
Requires-Dist: bitsandbytes>=0.41.0
Requires-Dist: requests>=2.31.0
Requires-Dist: huggingface_hub>=0.23.0
Provides-Extra: dev
Requires-Dist: pytest>=7.0.0; extra == "dev"
Requires-Dist: pytest-cov>=3.0.0; extra == "dev"
Requires-Dist: black>=22.0.0; extra == "dev"
Requires-Dist: isort>=5.10.0; extra == "dev"
Requires-Dist: flake8>=4.0.0; extra == "dev"
Requires-Dist: mypy>=0.950; extra == "dev"
Provides-Extra: training
Requires-Dist: wandb>=0.12.0; extra == "training"
Requires-Dist: tensorboard>=2.8.0; extra == "training"
Dynamic: author
Dynamic: home-page
Dynamic: license-file
Dynamic: requires-python
